pychemy/__init__.py
pychemy/adducts.py
pychemy/amino_acids.py
pychemy/chem_structure.py
pychemy/elements.py
pychemy/inchi.py
pychemy/inchi_converter.py
pychemy/molmass.py
pychemy/peptide_sets.py
pychemy/peptides.py
pychemy/resources/STEPP/STEPP_NormFactor_mean.txt
pychemy/resources/STEPP/STEPP_NormFactor_std.txt
pychemy/resources/STEPP/STEPP_SupportVectors.txt
pychemy/resources/STEPP/STEPP_Weights.txt
pychemy-0.5.0.dist-info/LICENSE.txt
pychemy-0.5.0.dist-info/METADATA
pychemy-0.5.0.dist-info/WHEEL
pychemy-0.5.0.dist-info/top_level.txt
pychemy-0.5.0.dist-info/zip-safe
pychemy-0.5.0.dist-info/RECORD
