Metadata-Version: 2.1
Name: pychemy
Version: 0.5.0
Summary: Helpers for handling chemical formulas in Python
Home-page: https://github.com/ginkgobioworks/pychemy
Author: Benjie Chen, Ginkgo Bioworks, Christoph Gohlke
Author-email: benjie@ginkgobioworks.com, devs@ginkgobioworks.com, cgohlke@uci.edu
License: MIT
Keywords: chemistry mass spectrometry chemoinformatics analysis molecular
Platform: UNKNOWN
Classifier: Development Status :: 5 - Production/Stable
Classifier: Environment :: Other Environment
Classifier: Intended Audience :: Developers
Classifier: Intended Audience :: Science/Research
Classifier: License :: OSI Approved :: MIT License
Classifier: Natural Language :: English
Classifier: Operating System :: OS Independent
Classifier: Programming Language :: Python :: 2.7
Classifier: Programming Language :: Python :: 3.5
Classifier: Topic :: Scientific/Engineering :: Artificial Intelligence
Classifier: Topic :: Scientific/Engineering :: Artificial Life
Classifier: Topic :: Scientific/Engineering :: Bio-Informatics
Classifier: Topic :: Scientific/Engineering :: Chemistry
Classifier: Topic :: Scientific/Engineering :: Information Analysis
Classifier: Topic :: Scientific/Engineering :: Mathematics
Classifier: Topic :: Scientific/Engineering :: Visualization
Classifier: Topic :: Software Development :: Libraries :: Python Modules
Requires-Python: >=2.7, !=3.0.*, !=3.1.*, !=3.2.*, !=3.3.*, !=3.4.*, <4
Requires-Dist: matplotlib
Requires-Dist: networkx (~=1.0)
Requires-Dist: numpy
Requires-Dist: openbabel
